CHANGELOG.txt
MANIFEST.in
README.in
README.txt
TODO.txt
dev.cfg
sample-prod.cfg
setup.cfg
setup.py
spammcan.kpf
start-spammcan.py
test.cfg
SpammCan.egg-info/PKG-INFO
SpammCan.egg-info/SOURCES.txt
SpammCan.egg-info/dependency_links.txt
SpammCan.egg-info/entry_points.txt
SpammCan.egg-info/not-zip-safe
SpammCan.egg-info/paster_plugins.txt
SpammCan.egg-info/requires.txt
SpammCan.egg-info/top_level.txt
doc/index.html
doc/rest.css
doc/api/api-objects.txt
doc/api/class-tree.html
doc/api/crarr.png
doc/api/epydoc.css
doc/api/epydoc.js
doc/api/exceptions.AssertionError-class.html
doc/api/formencode.api.NoDefault-class.html
doc/api/formencode.declarative.DeclarativeMeta-class.html
doc/api/help.html
doc/api/identifier-index.html
doc/api/index.html
doc/api/module-tree.html
doc/api/redirect.html
doc/api/spammcan-module.html
doc/api/spammcan-pysrc.html
doc/api/spammcan.bootstrap-module.html
doc/api/spammcan.bootstrap-pysrc.html
doc/api/spammcan.commands-module.html
doc/api/spammcan.commands-pysrc.html
doc/api/spammcan.commands.ConfigurationError-class.html
doc/api/spammcan.config-module.html
doc/api/spammcan.config-pysrc.html
doc/api/spammcan.controllers-module.html
doc/api/spammcan.controllers-pysrc.html
doc/api/spammcan.controllers.Root-class.html
doc/api/spammcan.forms-module.html
doc/api/spammcan.forms-pysrc.html
doc/api/spammcan.forms.base-module.html
doc/api/spammcan.forms.base-pysrc.html
doc/api/spammcan.forms.base.PasteFormFields-class.html
doc/api/spammcan.forms.base.PasteFormSchema-class.html
doc/api/spammcan.forms.base.StyleSelectForm-class.html
doc/api/spammcan.forms.base.StyleSelectForm.fields-class.html
doc/api/spammcan.forms.validators-module.html
doc/api/spammcan.forms.validators-pysrc.html
doc/api/spammcan.forms.validators.Range-class.html
doc/api/spammcan.forms.validators.SpamBayesFilter-class.html
doc/api/spammcan.forms.validators.ValidFormat-class.html
doc/api/spammcan.forms.validators.ValidModelValue-class.html
doc/api/spammcan.forms.validators.ValidPasteGuid-class.html
doc/api/spammcan.forms.validators.ValidStyle-class.html
doc/api/spammcan.json-module.html
doc/api/spammcan.json-pysrc.html
doc/api/spammcan.model-module.html
doc/api/spammcan.model-pysrc.html
doc/api/spammcan.model.Format-class.html
