Metadata-Version: 1.0
Name: SpammCan
Version: 0.2b
Summary: A simple pastbin built on TurboGears and Pygments.
Home-page: http://chrisarndt.de/project/spammcan/
Author: Christopher Arndt
Author-email: chris@chrisarndt.de
License: MIT, Zope Public License (rest.py)
Download-URL: http://cheeseshop.python.org/pypi/SpammCan
Keywords: turbogears.app
Platform: UNKNOWN
Classifier: Development Status :: 4 - Beta
Classifier: Operating System :: OS Independent
Classifier: Programming Language :: Python
Classifier: Topic :: Software Development :: Libraries :: Python Modules
Classifier: Framework :: TurboGears
Classifier: Framework :: TurboGears :: Applications
